odoo/addons/account_avatax/README.rst
odoo/addons/account_avatax/__init__.py
odoo/addons/account_avatax/__manifest__.py
odoo/addons/account_avatax/data/avalara_salestax_data.xml
odoo/addons/account_avatax/data/avalara_salestax_exemptions.xml
odoo/addons/account_avatax/i18n/account_avatax.pot
odoo/addons/account_avatax/models/__init__.py
odoo/addons/account_avatax/models/account_fiscal_position.py
odoo/addons/account_avatax/models/account_move.py
odoo/addons/account_avatax/models/account_tax.py
odoo/addons/account_avatax/models/avalara_salestax.py
odoo/addons/account_avatax/models/avatax_rest_api.py
odoo/addons/account_avatax/models/partner.py
odoo/addons/account_avatax/models/product.py
odoo/addons/account_avatax/models/res_company.py
odoo/addons/account_avatax/readme/CONFIGURE.rst
odoo/addons/account_avatax/readme/CONTRIBUTORS.rst
odoo/addons/account_avatax/readme/CREDITS.rst
odoo/addons/account_avatax/readme/DESCRIPTION.rst
odoo/addons/account_avatax/readme/INSTALL.rst
odoo/addons/account_avatax/readme/ROADMAP.rst
odoo/addons/account_avatax/readme/USAGE.rst
odoo/addons/account_avatax/security/avalara_salestax_security.xml
odoo/addons/account_avatax/security/ir.model.access.csv
odoo/addons/account_avatax/static/description/ATC1.png
odoo/addons/account_avatax/static/description/ATC10.png
odoo/addons/account_avatax/static/description/ATC11.png
odoo/addons/account_avatax/static/description/ATC12.png
odoo/addons/account_avatax/static/description/ATC13.png
odoo/addons/account_avatax/static/description/ATC14.png
odoo/addons/account_avatax/static/description/ATC15.png
odoo/addons/account_avatax/static/description/ATC16.png
odoo/addons/account_avatax/static/description/ATC17.png
odoo/addons/account_avatax/static/description/ATC18.png
odoo/addons/account_avatax/static/description/ATC19.png
odoo/addons/account_avatax/static/description/ATC2.png
odoo/addons/account_avatax/static/description/ATC20.png
odoo/addons/account_avatax/static/description/ATC21.png
odoo14_addon_account_avatax-14.0.3.1.0.dist-info/METADATA
odoo14_addon_account_avatax-14.0.3.1.0.dist-info/WHEEL
odoo14_addon_account_avatax-14.0.3.1.0.dist-info/top_level.txt
odoo14_addon_account_avatax-14.0.3.1.0.dist-info/RECORD
