Metadata-Version: 2.1
Name: odoo14-addon-account-avatax
Version: 14.0.3.1.0
Summary: Automatic Tax application using the Avalara Avatax Service
Home-page: https://github.com/OCA/account-fiscal-rule
Author: Open Source Integrators, Fabrice Henrion,Sodexis, Odoo Community Association (OCA)
Author-email: support@odoo-community.org
License: AGPL-3
Platform: UNKNOWN
Classifier: Programming Language :: Python
Classifier: Framework :: Odoo
Classifier: Framework :: Odoo :: 14.0
Classifier: License :: OSI Approved :: GNU Affero General Public License v3
Classifier: Development Status :: 3 - Alpha
Requires-Python: >=3.6
Requires-Dist: Avalara
Requires-Dist: odoo (<14.1dev,>=14.0a)
